{
  "version": "2.3.6",
  "flags": {},
  "shapes": [
    {
      "label": "cdark",
      "points": [
        [
          366.03773584905633,
          30.566037735849307
        ],
        [
          1744.3396226415093,
          30.566037735849307
        ],
        [
          1744.3396226415093,
          51.32075471698114
        ],
        [
          366.03773584905633,
          51.32075471698114
        ]
      ],
      "group_id": 5,
      "description": "",
      "difficult": false,
      "shape_type": "rectangle",
      "flags": {},
      "attributes": {}
    },
    {
      "label": "cdark",
      "points": [
        [
          364.6326776395026,
          71.71417101565636
        ],
        [
          1742.4528301886792,
          71.71417101565636
        ],
        [
          1742.4528301886792,
          93.77358490566036
        ],
        [
          364.6326776395026,
          93.77358490566036
        ]
      ],
      "group_id": 6,
      "description": "",
      "difficult": false,
      "shape_type": "rectangle",
      "flags": {},
      "attributes": {}
    },
    {
      "label": "cdark",
      "points": [
        [
          367.1015656362905,
          120.40947410678419
        ],
        [
          1743.5166599759123,
          120.40947410678419
        ],
        [
          1743.5166599759123,
          142.10758731433128
        ],
        [
          367.1015656362905,
          142.10758731433128
        ]
      ],
      "group_id": 7,
      "description": "",
      "difficult": false,
      "shape_type": "rectangle",
      "flags": {},
      "attributes": {}
    },
    {
      "label": "cdark",
      "points": [
        [
          365.57607386591775,
          173.0188679245283
        ],
        [
          1739.622641509434,
          173.0188679245283
        ],
        [
          1739.622641509434,
          191.88679245283015
        ],
        [
          365.57607386591775,
          191.88679245283015
        ]
      ],
      "group_id": 8,
      "description": "",
      "difficult": false,
      "shape_type": "rectangle",
      "flags": {},
      "attributes": {}
    },
    {
      "label": "cdark",
      "points": [
        [
          364.15094339622607,
          215.4716981132076
        ],
        [
          1745.2830188679243,
          215.4716981132076
        ],
        [
          1745.2830188679243,
          237.16981132075477
        ],
        [
          364.15094339622607,
          237.16981132075477
        ]
      ],
      "group_id": 9,
      "description": "",
      "difficult": false,
      "shape_type": "rectangle",
      "flags": {},
      "attributes": {}
    },
    {
      "label": "cdark",
      "points": [
        [
          366.2786029706938,
          262.6415094339623
        ],
        [
          1744.339622641509,
          262.6415094339623
        ],
        [
          1744.339622641509,
          281.5094339622643
        ],
        [
          366.2786029706938,
          281.5094339622643
        ]
      ],
      "group_id": 10,
      "description": "",
      "difficult": false,
      "shape_type": "rectangle",
      "flags": {},
      "attributes": {}
    },
    {
      "label": "cdark",
      "points": [
        [
          367.2219991971112,
          307.0814933761546
        ],
        [
          1743.6370935367336,
          307.0814933761546
        ],
        [
          1743.6370935367336,
          327.83621035728646
        ],
        [
          367.2219991971112,
          327.83621035728646
        ]
      ],
      "group_id": 11,
      "description": "",
      "difficult": false,
      "shape_type": "rectangle",
      "flags": {},
      "attributes": {}
    },
    {
      "label": "cdark",
      "points": [
        [
          368.044961862705,
          354.6126053793659
        ],
        [
          1744.4600562023277,
          354.6126053793659
        ],
        [
          1744.4600562023277,
          376.31071858691325
        ],
        [
          368.044961862705,
          376.31071858691325
        ]
      ],
      "group_id": 12,
      "description": "",
      "difficult": false,
      "shape_type": "rectangle",
      "flags": {},
      "attributes": {}
    },
    {
      "label": "cdark",
      "points": [
        [
          366.981132075472,
          398.01886792452837
        ],
        [
          1749.0566037735848,
          398.01886792452837
        ],
        [
          1749.0566037735848,
          420.6603773584906
        ],
        [
          366.981132075472,
          420.6603773584906
        ]
      ],
      "group_id": 13,
      "description": "",
      "difficult": false,
      "shape_type": "rectangle",
      "flags": {},
      "attributes": {}
    },
    {
      "label": "cdark",
      "points": [
        [
          368.86792452830286,
          445.2990766760337
        ],
        [
          1745.2830188679245,
          445.2990766760337
        ],
        [
          1745.2830188679245,
          466.99718988358086
        ],
        [
          368.86792452830286,
          466.99718988358086
        ]
      ],
      "group_id": 14,
      "description": "",
      "difficult": false,
      "shape_type": "rectangle",
      "flags": {},
      "attributes": {}
    },
    {
      "label": "cdark",
      "points": [
        [
          366.981132075472,
          493.1714171015653
        ],
        [
          1739.622641509434,
          493.1714171015653
        ],
        [
          1739.622641509434,
          515.4716981132071
        ],
        [
          366.981132075472,
          515.4716981132071
        ]
      ],
      "group_id": 15,
      "description": "",
      "difficult": false,
      "shape_type": "rectangle",
      "flags": {},
      "attributes": {}
    },
    {
      "label": "cdark",
      "points": [
        [
          365.09433962264114,
          541.0437575270983
        ],
        [
          1741.5094339622642,
          541.0437575270983
        ],
        [
          1741.5094339622642,
          563.6852669610605
        ],
        [
          365.09433962264114,
          563.6852669610605
        ]
      ],
      "group_id": 16,
      "description": "",
      "difficult": false,
      "shape_type": "rectangle",
      "flags": {},
      "attributes": {}
    },
    {
      "label": "cdark",
      "points": [
        [
          367.10156563628965,
          585.2830188679246
        ],
        [
          1741.5094339622633,
          585.2830188679246
        ],
        [
          1741.5094339622633,
          607.9245283018872
        ],
        [
          367.10156563628965,
          607.9245283018872
        ]
      ],
      "group_id": 17,
      "description": "",
      "difficult": false,
      "shape_type": "rectangle",
      "flags": {},
      "attributes": {}
    },
    {
      "label": "cdark",
      "points": [
        [
          366.5194700923318,
          635.2830188679251
        ],
        [
          1738.6792452830182,
          635.2830188679251
        ],
        [
          1738.6792452830182,
          656.9811320754721
        ],
        [
          366.5194700923318,
          656.9811320754721
        ]
      ],
      "group_id": 18,
      "description": "",
      "difficult": false,
      "shape_type": "rectangle",
      "flags": {},
      "attributes": {}
    },
    {
      "label": "cdark",
      "points": [
        [
          366.0377358490571,
          681.5094339622638
        ],
        [
          1743.396226415095,
          681.5094339622638
        ],
        [
          1743.396226415095,
          702.9666800481732
        ],
        [
          366.0377358490571,
          702.9666800481732
        ]
      ],
      "group_id": 19,
      "description": "",
      "difficult": false,
      "shape_type": "rectangle",
      "flags": {},
      "attributes": {}
    },
    {
      "label": "cdark",
      "points": [
        [
          364.97390606182324,
          725.1264552388601
        ],
        [
          1748.11320754717,
          725.1264552388601
        ],
        [
          1748.11320754717,
          745.6603773584906
        ],
        [
          364.97390606182324,
          745.6603773584906
        ]
      ],
      "group_id": 20,
      "description": "",
      "difficult": false,
      "shape_type": "rectangle",
      "flags": {},
      "attributes": {}
    },
    {
      "label": "cdark",
      "points": [
        [
          365.09433962264166,
          773.0188679245288
        ],
        [
          1745.2830188679245,
          773.0188679245288
        ],
        [
          1745.2830188679245,
          795.6603773584907
        ],
        [
          365.09433962264166,
          795.6603773584907
        ]
      ],
      "group_id": 21,
      "description": "",
      "difficult": false,
      "shape_type": "rectangle",
      "flags": {},
      "attributes": {}
    },
    {
      "label": "cdark",
      "points": [
        [
          364.15094339622675,
          819.2452830188682
        ],
        [
          1739.6226415094347,
          819.2452830188682
        ],
        [
          1739.6226415094347,
          840.9433962264153
        ],
        [
          364.15094339622675,
          840.9433962264153
        ]
      ],
      "group_id": 22,
      "description": "",
      "difficult": false,
      "shape_type": "rectangle",
      "flags": {},
      "attributes": {}
    },
    {
      "label": "cdark",
      "points": [
        [
          364.1509433962259,
          866.4150943396222
        ],
        [
          1741.5094339622642,
          866.4150943396222
        ],
        [
          1741.5094339622642,
          889.9999999999997
        ],
        [
          364.1509433962259,
          889.9999999999997
        ]
      ],
      "group_id": 23,
      "description": "",
      "difficult": false,
      "shape_type": "rectangle",
      "flags": {},
      "attributes": {}
    },
    {
      "label": "cdark",
      "points": [
        [
          365.09433962264205,
          913.5849056603784
        ],
        [
          1738.6792452830186,
          913.5849056603784
        ],
        [
          1738.6792452830186,
          936.2264150943406
        ],
        [
          365.09433962264205,
          936.2264150943406
        ]
      ],
      "group_id": 24,
      "description": "",
      "difficult": false,
      "shape_type": "rectangle",
      "flags": {},
      "attributes": {}
    },
    {
      "label": "cdark",
      "points": [
        [
          365.0943396226416,
          959.8113207547168
        ],
        [
          1742.452830188679,
          959.8113207547168
        ],
        [
          1742.452830188679,
          983.3962264150945
        ],
        [
          365.0943396226416,
          983.3962264150945
        ]
      ],
      "group_id": 25,
      "description": "",
      "difficult": false,
      "shape_type": "rectangle",
      "flags": {},
      "attributes": {}
    },
    {
      "label": "cdark",
      "points": [
        [
          364.15094339622635,
          1010.7547169811321
        ],
        [
          1738.6792452830186,
          1010.7547169811321
        ],
        [
          1738.6792452830186,
          1031.5094339622642
        ],
        [
          364.15094339622635,
          1031.5094339622642
        ]
      ],
      "group_id": 26,
      "description": "",
      "difficult": false,
      "shape_type": "rectangle",
      "flags": {},
      "attributes": {}
    },
    {
      "label": "cdark",
      "points": [
        [
          365.09433962264137,
          1052.2641509433963
        ],
        [
          1739.6226415094343,
          1052.2641509433963
        ],
        [
          1739.6226415094343,
          1074.9056603773583
        ],
        [
          365.09433962264137,
          1074.9056603773583
        ]
      ],
      "group_id": 27,
      "description": "",
      "difficult": false,
      "shape_type": "rectangle",
      "flags": {},
      "attributes": {}
    }
  ],
  "imagePath": "frame_002640.jpg",
  "imageData": null,
  "imageHeight": 1080,
  "imageWidth": 2100
}