{
  "version": "2.3.6",
  "flags": {},
  "shapes": [
    {
      "label": "cdark",
      "points": [
        [
          354.4444444444445,
          134.44444444444412
        ],
        [
          1732.2222222222222,
          134.44444444444412
        ],
        [
          1732.2222222222222,
          154.44444444444417
        ],
        [
          354.4444444444445,
          154.44444444444417
        ]
      ],
      "group_id": 2,
      "description": "",
      "difficult": false,
      "shape_type": "rectangle",
      "flags": {},
      "attributes": {}
    },
    {
      "label": "cdark",
      "points": [
        [
          363.3333333333336,
          183.33333333333331
        ],
        [
          1727.7777777777778,
          183.33333333333331
        ],
        [
          1727.7777777777778,
          201.1111111111111
        ],
        [
          363.3333333333336,
          201.1111111111111
        ]
      ],
      "group_id": 3,
      "description": "",
      "difficult": false,
      "shape_type": "rectangle",
      "flags": {},
      "attributes": {}
    },
    {
      "label": "cdark",
      "points": [
        [
          361.1111111111112,
          225.55555555555543
        ],
        [
          1732.2222222222226,
          225.55555555555543
        ],
        [
          1732.2222222222226,
          245.55555555555543
        ],
        [
          361.1111111111112,
          245.55555555555543
        ]
      ],
      "group_id": 4,
      "description": "",
      "difficult": false,
      "shape_type": "rectangle",
      "flags": {},
      "attributes": {}
    },
    {
      "label": "cdark",
      "points": [
        [
          365.5555555555558,
          274.4444444444442
        ],
        [
          1738.8888888888891,
          274.4444444444442
        ],
        [
          1738.8888888888891,
          294.4444444444442
        ],
        [
          365.5555555555558,
          294.4444444444442
        ]
      ],
      "group_id": 5,
      "description": "",
      "difficult": false,
      "shape_type": "rectangle",
      "flags": {},
      "attributes": {}
    },
    {
      "label": "cdark",
      "points": [
        [
          361.1111111111114,
          321.11111111111114
        ],
        [
          1732.2222222222226,
          321.11111111111114
        ],
        [
          1732.2222222222226,
          341.11111111111114
        ],
        [
          361.1111111111114,
          341.11111111111114
        ]
      ],
      "group_id": 6,
      "description": "",
      "difficult": false,
      "shape_type": "rectangle",
      "flags": {},
      "attributes": {}
    },
    {
      "label": "cdark",
      "points": [
        [
          363.33333333333314,
          365.55555555555566
        ],
        [
          1727.7777777777778,
          365.55555555555566
        ],
        [
          1727.7777777777778,
          385.55555555555566
        ],
        [
          363.33333333333314,
          385.55555555555566
        ]
      ],
      "group_id": 7,
      "description": "",
      "difficult": false,
      "shape_type": "rectangle",
      "flags": {},
      "attributes": {}
    },
    {
      "label": "cdark",
      "points": [
        [
          365.5555555555559,
          407.777777777778
        ],
        [
          1730.0000000000007,
          407.777777777778
        ],
        [
          1730.0000000000007,
          430.0000000000002
        ],
        [
          365.5555555555559,
          430.0000000000002
        ]
      ],
      "group_id": 8,
      "description": "",
      "difficult": false,
      "shape_type": "rectangle",
      "flags": {},
      "attributes": {}
    },
    {
      "label": "cdark",
      "points": [
        [
          367.7777777777779,
          456.66666666666686
        ],
        [
          1738.8888888888887,
          456.66666666666686
        ],
        [
          1738.8888888888887,
          476.66666666666686
        ],
        [
          367.7777777777779,
          476.66666666666686
        ]
      ],
      "group_id": 9,
      "description": "",
      "difficult": false,
      "shape_type": "rectangle",
      "flags": {},
      "attributes": {}
    },
    {
      "label": "cdark",
      "points": [
        [
          365.55555555555554,
          507.7777777777774
        ],
        [
          1734.4444444444448,
          507.7777777777774
        ],
        [
          1734.4444444444448,
          527.7777777777774
        ],
        [
          365.55555555555554,
          527.7777777777774
        ]
      ],
      "group_id": 10,
      "description": "",
      "difficult": false,
      "shape_type": "rectangle",
      "flags": {},
      "attributes": {}
    },
    {
      "label": "cdark",
      "points": [
        [
          370.00000000000017,
          552.2222222222225
        ],
        [
          1736.6666666666674,
          552.2222222222225
        ],
        [
          1736.6666666666674,
          572.2222222222225
        ],
        [
          370.00000000000017,
          572.2222222222225
        ]
      ],
      "group_id": 11,
      "description": "",
      "difficult": false,
      "shape_type": "rectangle",
      "flags": {},
      "attributes": {}
    },
    {
      "label": "cdark",
      "points": [
        [
          365.55555555555605,
          594.4444444444446
        ],
        [
          1736.6666666666665,
          594.4444444444446
        ],
        [
          1736.6666666666665,
          614.4444444444446
        ],
        [
          365.55555555555605,
          614.4444444444446
        ]
      ],
      "group_id": 12,
      "description": "",
      "difficult": false,
      "shape_type": "rectangle",
      "flags": {},
      "attributes": {}
    },
    {
      "label": "cdark",
      "points": [
        [
          367.77777777777754,
          641.1111111111106
        ],
        [
          1732.2222222222217,
          641.1111111111106
        ],
        [
          1732.2222222222217,
          667.7777777777774
        ],
        [
          367.77777777777754,
          667.7777777777774
        ]
      ],
      "group_id": 13,
      "description": "",
      "difficult": false,
      "shape_type": "rectangle",
      "flags": {},
      "attributes": {}
    },
    {
      "label": "cdark",
      "points": [
        [
          372.22222222222223,
          685.5555555555553
        ],
        [
          1741.1111111111113,
          685.5555555555553
        ],
        [
          1741.1111111111113,
          712.2222222222221
        ],
        [
          372.22222222222223,
          712.2222222222221
        ]
      ],
      "group_id": 14,
      "description": "",
      "difficult": false,
      "shape_type": "rectangle",
      "flags": {},
      "attributes": {}
    },
    {
      "label": "cdark",
      "points": [
        [
          372.22222222222246,
          738.8888888888893
        ],
        [
          1741.1111111111109,
          738.8888888888893
        ],
        [
          1741.1111111111109,
          761.1111111111115
        ],
        [
          372.22222222222246,
          761.1111111111115
        ]
      ],
      "group_id": 15,
      "description": "",
      "difficult": false,
      "shape_type": "rectangle",
      "flags": {},
      "attributes": {}
    },
    {
      "label": "cdark",
      "points": [
        [
          376.6666666666666,
          825.5555555555552
        ],
        [
          1734.4444444444443,
          825.5555555555552
        ],
        [
          1734.4444444444443,
          845.5555555555552
        ],
        [
          376.6666666666666,
          845.5555555555552
        ]
      ],
      "group_id": 16,
      "description": "",
      "difficult": false,
      "shape_type": "rectangle",
      "flags": {},
      "attributes": {}
    },
    {
      "label": "cdark",
      "points": [
        [
          365.55555555555566,
          778.8888888888886
        ],
        [
          1743.333333333333,
          778.8888888888886
        ],
        [
          1743.333333333333,
          805.5555555555554
        ],
        [
          365.55555555555566,
          805.5555555555554
        ]
      ],
      "group_id": 17,
      "description": "",
      "difficult": false,
      "shape_type": "rectangle",
      "flags": {},
      "attributes": {}
    },
    {
      "label": "cdark",
      "points": [
        [
          367.77777777777834,
          878.8888888888891
        ],
        [
          1738.8888888888891,
          878.8888888888891
        ],
        [
          1738.8888888888891,
          901.1111111111113
        ],
        [
          367.77777777777834,
          901.1111111111113
        ]
      ],
      "group_id": 18,
      "description": "",
      "difficult": false,
      "shape_type": "rectangle",
      "flags": {},
      "attributes": {}
    },
    {
      "label": "cdark",
      "points": [
        [
          369.9999999999997,
          927.7777777777783
        ],
        [
          1741.1111111111109,
          927.7777777777783
        ],
        [
          1741.1111111111109,
          947.7777777777783
        ],
        [
          369.9999999999997,
          947.7777777777783
        ]
      ],
      "group_id": 19,
      "description": "",
      "difficult": false,
      "shape_type": "rectangle",
      "flags": {},
      "attributes": {}
    },
    {
      "label": "cdark",
      "points": [
        [
          367.7777777777774,
          972.2222222222217
        ],
        [
          1741.1111111111109,
          972.2222222222217
        ],
        [
          1741.1111111111109,
          992.2222222222214
        ],
        [
          367.7777777777774,
          992.2222222222214
        ]
      ],
      "group_id": 20,
      "description": "",
      "difficult": false,
      "shape_type": "rectangle",
      "flags": {},
      "attributes": {}
    },
    {
      "label": "cdark",
      "points": [
        [
          372.22222222222274,
          1020.0000000000006
        ],
        [
          1747.7777777777774,
          1020.0000000000006
        ],
        [
          1747.7777777777774,
          1037.7777777777785
        ],
        [
          372.22222222222274,
          1037.7777777777785
        ]
      ],
      "group_id": 21,
      "description": "",
      "difficult": false,
      "shape_type": "rectangle",
      "flags": {},
      "attributes": {}
    },
    {
      "label": "udark",
      "points": [
        [
          354.44444444444423,
          8.000000000000483
        ],
        [
          1721.1111111111131,
          8.000000000000483
        ],
        [
          1721.1111111111131,
          30.22222222222355
        ],
        [
          354.44444444444423,
          30.22222222222355
        ]
      ],
      "group_id": 1,
      "description": "",
      "difficult": false,
      "shape_type": "rectangle",
      "flags": {},
      "attributes": {}
    },
    {
      "label": "cdark",
      "points": [
        [
          354.4444444444443,
          83.33333333333344
        ],
        [
          1727.7777777777778,
          83.33333333333344
        ],
        [
          1727.7777777777778,
          112.22222222222229
        ],
        [
          354.4444444444443,
          112.22222222222229
        ]
      ],
      "group_id": 1,
      "description": "",
      "difficult": false,
      "shape_type": "rectangle",
      "flags": {},
      "attributes": {}
    },
    {
      "label": "cdark",
      "points": [
        [
          356.66666666666646,
          44.888888888889056
        ],
        [
          1721.1111111111127,
          44.888888888889056
        ],
        [
          1721.1111111111127,
          67.11111111111146
        ],
        [
          356.66666666666646,
          67.11111111111146
        ]
      ],
      "group_id": 23,
      "description": "",
      "difficult": false,
      "shape_type": "rectangle",
      "flags": {},
      "attributes": {}
    }
  ],
  "imagePath": "frame_024360.jpg",
  "imageData": null,
  "imageHeight": 1080,
  "imageWidth": 2100
}