{
  "version": "2.3.6",
  "flags": {},
  "shapes": [
    {
      "label": "cdark",
      "points": [
        [
          353.70859538784026,
          242.68763102725364
        ],
        [
          1732.9538784067086,
          242.68763102725364
        ],
        [
          1732.9538784067086,
          264.85744234800853
        ],
        [
          353.70859538784026,
          264.85744234800853
        ]
      ],
      "group_id": 5,
      "description": "",
      "difficult": false,
      "shape_type": "rectangle",
      "flags": {},
      "attributes": {}
    },
    {
      "label": "cdark",
      "points": [
        [
          355.0729292118294,
          294.1670012043357
        ],
        [
          1732.8930817610067,
          294.1670012043357
        ],
        [
          1732.8930817610067,
          316.22641509433964
        ],
        [
          355.0729292118294,
          316.22641509433964
        ]
      ],
      "group_id": 6,
      "description": "",
      "difficult": false,
      "shape_type": "rectangle",
      "flags": {},
      "attributes": {}
    },
    {
      "label": "cdark",
      "points": [
        [
          359.82693251260116,
          339.3612560774343
        ],
        [
          1736.2420268522233,
          339.3612560774343
        ],
        [
          1736.2420268522233,
          361.0593692849814
        ],
        [
          359.82693251260116,
          361.0593692849814
        ]
      ],
      "group_id": 7,
      "description": "",
      "difficult": false,
      "shape_type": "rectangle",
      "flags": {},
      "attributes": {}
    },
    {
      "label": "cdark",
      "points": [
        [
          366.5194700923321,
          388.53249475891005
        ],
        [
          1740.5660377358488,
          388.53249475891005
        ],
        [
          1740.5660377358488,
          408.34381551362685
        ],
        [
          366.5194700923321,
          408.34381551362685
        ]
      ],
      "group_id": 8,
      "description": "",
      "difficult": false,
      "shape_type": "rectangle",
      "flags": {},
      "attributes": {}
    },
    {
      "label": "cdark",
      "points": [
        [
          360.0419287211741,
          429.0356394129973
        ],
        [
          1741.174004192872,
          429.0356394129973
        ],
        [
          1741.174004192872,
          450.73375262054446
        ],
        [
          360.0419287211741,
          450.73375262054446
        ]
      ],
      "group_id": 9,
      "description": "",
      "difficult": false,
      "shape_type": "rectangle",
      "flags": {},
      "attributes": {}
    },
    {
      "label": "cdark",
      "points": [
        [
          354.22409563316756,
          477.48427672955927
        ],
        [
          1732.2851153039837,
          477.48427672955927
        ],
        [
          1732.2851153039837,
          496.3522012578612
        ],
        [
          354.22409563316756,
          496.3522012578612
        ]
      ],
      "group_id": 10,
      "description": "",
      "difficult": false,
      "shape_type": "rectangle",
      "flags": {},
      "attributes": {}
    },
    {
      "label": "cdark",
      "points": [
        [
          354.559525402561,
          521.9242606717528
        ],
        [
          1730.9746197421837,
          521.9242606717528
        ],
        [
          1730.9746197421837,
          542.6789776528846
        ],
        [
          354.559525402561,
          542.6789776528846
        ]
      ],
      "group_id": 11,
      "description": "",
      "difficult": false,
      "shape_type": "rectangle",
      "flags": {},
      "attributes": {}
    },
    {
      "label": "cdark",
      "points": [
        [
          355.71791783754793,
          571.0696284401621
        ],
        [
          1732.1330121771707,
          571.0696284401621
        ],
        [
          1732.1330121771707,
          592.7677416477094
        ],
        [
          355.71791783754793,
          592.7677416477094
        ]
      ],
      "group_id": 12,
      "description": "",
      "difficult": false,
      "shape_type": "rectangle",
      "flags": {},
      "attributes": {}
    },
    {
      "label": "cdark",
      "points": [
        [
          359.70649895178224,
          616.9706498951781
        ],
        [
          1741.781970649895,
          616.9706498951781
        ],
        [
          1741.781970649895,
          639.6121593291404
        ],
        [
          359.70649895178224,
          639.6121593291404
        ]
      ],
      "group_id": 13,
      "description": "",
      "difficult": false,
      "shape_type": "rectangle",
      "flags": {},
      "attributes": {}
    },
    {
      "label": "cdark",
      "points": [
        [
          357.8197064989524,
          665.5296846424905
        ],
        [
          1734.2348008385748,
          665.5296846424905
        ],
        [
          1734.2348008385748,
          687.2277978500376
        ],
        [
          357.8197064989524,
          687.2277978500376
        ]
      ],
      "group_id": 14,
      "description": "",
      "difficult": false,
      "shape_type": "rectangle",
      "flags": {},
      "attributes": {}
    },
    {
      "label": "cdark",
      "points": [
        [
          359.37106918238976,
          711.5152326151922
        ],
        [
          1732.0125786163521,
          711.5152326151922
        ],
        [
          1732.0125786163521,
          733.8155136268341
        ],
        [
          359.37106918238976,
          733.8155136268341
        ]
      ],
      "group_id": 15,
      "description": "",
      "difficult": false,
      "shape_type": "rectangle",
      "flags": {},
      "attributes": {}
    },
    {
      "label": "cdark",
      "points": [
        [
          358.7631027253663,
          757.1653508185024
        ],
        [
          1735.178197064989,
          757.1653508185024
        ],
        [
          1735.178197064989,
          779.8068602524646
        ],
        [
          358.7631027253663,
          779.8068602524646
        ]
      ],
      "group_id": 16,
      "description": "",
      "difficult": false,
      "shape_type": "rectangle",
      "flags": {},
      "attributes": {}
    },
    {
      "label": "cdark",
      "points": [
        [
          357.2692805209867,
          806.457023060797
        ],
        [
          1728.8469601677148,
          806.457023060797
        ],
        [
          1728.8469601677148,
          828.155136268344
        ],
        [
          357.2692805209867,
          828.155136268344
        ]
      ],
      "group_id": 17,
      "description": "",
      "difficult": false,
      "shape_type": "rectangle",
      "flags": {},
      "attributes": {}
    },
    {
      "label": "cdark",
      "points": [
        [
          355.4083589812208,
          850.1257861635219
        ],
        [
          1727.5681341719078,
          850.1257861635219
        ],
        [
          1727.5681341719078,
          871.8238993710689
        ],
        [
          355.4083589812208,
          871.8238993710689
        ]
      ],
      "group_id": 18,
      "description": "",
      "difficult": false,
      "shape_type": "rectangle",
      "flags": {},
      "attributes": {}
    },
    {
      "label": "cdark",
      "points": [
        [
          356.8763102725372,
          896.0167714884698
        ],
        [
          1734.2348008385748,
          896.0167714884698
        ],
        [
          1734.2348008385748,
          917.4740175743792
        ],
        [
          356.8763102725372,
          917.4740175743792
        ]
      ],
      "group_id": 19,
      "description": "",
      "difficult": false,
      "shape_type": "rectangle",
      "flags": {},
      "attributes": {}
    },
    {
      "label": "cdark",
      "points": [
        [
          363.42254337838546,
          945.9650296623395
        ],
        [
          1746.5618448637326,
          945.9650296623395
        ],
        [
          1746.5618448637326,
          966.4989517819699
        ],
        [
          363.42254337838546,
          966.4989517819699
        ]
      ],
      "group_id": 20,
      "description": "",
      "difficult": false,
      "shape_type": "rectangle",
      "flags": {},
      "attributes": {}
    },
    {
      "label": "cdark",
      "points": [
        [
          359.0985324947589,
          990.6918238993713
        ],
        [
          1739.287211740042,
          990.6918238993713
        ],
        [
          1739.287211740042,
          1013.3333333333333
        ],
        [
          359.0985324947589,
          1013.3333333333333
        ]
      ],
      "group_id": 21,
      "description": "",
      "difficult": false,
      "shape_type": "rectangle",
      "flags": {},
      "attributes": {}
    },
    {
      "label": "cdark",
      "points": [
        [
          361.92872117400407,
          1036.1970649895197
        ],
        [
          1737.4004192872112,
          1036.1970649895197
        ],
        [
          1737.4004192872112,
          1057.8951781970668
        ],
        [
          361.92872117400407,
          1057.8951781970668
        ]
      ],
      "group_id": 22,
      "description": "",
      "difficult": false,
      "shape_type": "rectangle",
      "flags": {},
      "attributes": {}
    },
    {
      "label": "cdark",
      "points": [
        [
          352.0964360586993,
          9.75681341719222
        ],
        [
          1729.4549266247386,
          9.75681341719222
        ],
        [
          1729.4549266247386,
          33.341719077569095
        ],
        [
          352.0964360586993,
          33.341719077569095
        ]
      ],
      "group_id": 23,
      "description": "",
      "difficult": false,
      "shape_type": "rectangle",
      "flags": {},
      "attributes": {}
    },
    {
      "label": "cdark",
      "points": [
        [
          348.59538784067075,
          58.813417190774416
        ],
        [
          1721.2368972746344,
          58.813417190774416
        ],
        [
          1721.2368972746344,
          78.00209643605727
        ],
        [
          348.59538784067075,
          78.00209643605727
        ]
      ],
      "group_id": 1,
      "description": "",
      "difficult": false,
      "shape_type": "rectangle",
      "flags": {},
      "attributes": {}
    },
    {
      "label": "cdark",
      "points": [
        [
          352.22222222222234,
          108.99999999999997
        ],
        [
          1723.3333333333348,
          108.99999999999997
        ],
        [
          1723.3333333333348,
          126.77777777777811
        ],
        [
          352.22222222222234,
          126.77777777777811
        ]
      ],
      "group_id": 2,
      "description": "",
      "difficult": false,
      "shape_type": "rectangle",
      "flags": {},
      "attributes": {}
    },
    {
      "label": "cdark",
      "points": [
        [
          356.6666666666665,
          155.77777777777712
        ],
        [
          1736.6666666666674,
          155.77777777777712
        ],
        [
          1736.6666666666674,
          175.77777777777698
        ],
        [
          356.6666666666665,
          175.77777777777698
        ]
      ],
      "group_id": 3,
      "description": "",
      "difficult": false,
      "shape_type": "rectangle",
      "flags": {},
      "attributes": {}
    },
    {
      "label": "cdark",
      "points": [
        [
          349.9999999999998,
          202.55555555555583
        ],
        [
          1721.1111111111104,
          202.55555555555583
        ],
        [
          1721.1111111111104,
          220.33333333333354
        ],
        [
          349.9999999999998,
          220.33333333333354
        ]
      ],
      "group_id": 4,
      "description": "",
      "difficult": false,
      "shape_type": "rectangle",
      "flags": {},
      "attributes": {}
    }
  ],
  "imagePath": "frame_039960.jpg",
  "imageData": null,
  "imageHeight": 1080,
  "imageWidth": 2100
}