{
  "version": "2.3.6",
  "flags": {},
  "shapes": [
    {
      "label": "cdark",
      "points": [
        [
          364.81970649895135,
          244.90985324947587
        ],
        [
          1744.0649895178194,
          244.90985324947587
        ],
        [
          1744.0649895178194,
          267.07966457023076
        ],
        [
          364.81970649895135,
          267.07966457023076
        ]
      ],
      "group_id": 5,
      "description": "",
      "difficult": false,
      "shape_type": "rectangle",
      "flags": {},
      "attributes": {}
    },
    {
      "label": "cdark",
      "points": [
        [
          363.9618181007183,
          294.16700120433575
        ],
        [
          1741.7819706498954,
          294.16700120433575
        ],
        [
          1741.7819706498954,
          316.2264150943397
        ],
        [
          363.9618181007183,
          316.2264150943397
        ]
      ],
      "group_id": 6,
      "description": "",
      "difficult": false,
      "shape_type": "rectangle",
      "flags": {},
      "attributes": {}
    },
    {
      "label": "cdark",
      "points": [
        [
          357.604710290379,
          339.3612560774343
        ],
        [
          1734.019804630001,
          339.3612560774343
        ],
        [
          1734.019804630001,
          361.0593692849814
        ],
        [
          357.604710290379,
          361.0593692849814
        ]
      ],
      "group_id": 7,
      "description": "",
      "difficult": false,
      "shape_type": "rectangle",
      "flags": {},
      "attributes": {}
    },
    {
      "label": "cdark",
      "points": [
        [
          359.85280342566523,
          386.3102725366877
        ],
        [
          1733.899371069182,
          386.3102725366877
        ],
        [
          1733.899371069182,
          406.1215932914045
        ],
        [
          359.85280342566523,
          406.1215932914045
        ]
      ],
      "group_id": 8,
      "description": "",
      "difficult": false,
      "shape_type": "rectangle",
      "flags": {},
      "attributes": {}
    },
    {
      "label": "cdark",
      "points": [
        [
          353.37526205450746,
          431.2578616352198
        ],
        [
          1734.5073375262054,
          431.2578616352198
        ],
        [
          1734.5073375262054,
          452.955974842767
        ],
        [
          353.37526205450746,
          452.955974842767
        ]
      ],
      "group_id": 9,
      "description": "",
      "difficult": false,
      "shape_type": "rectangle",
      "flags": {},
      "attributes": {}
    },
    {
      "label": "cdark",
      "points": [
        [
          360.8907622998343,
          477.48427672955916
        ],
        [
          1738.9517819706502,
          477.48427672955916
        ],
        [
          1738.9517819706502,
          496.3522012578611
        ],
        [
          360.8907622998343,
          496.3522012578611
        ]
      ],
      "group_id": 10,
      "description": "",
      "difficult": false,
      "shape_type": "rectangle",
      "flags": {},
      "attributes": {}
    },
    {
      "label": "cdark",
      "points": [
        [
          356.7817476247833,
          524.1464828939751
        ],
        [
          1733.1968419644058,
          524.1464828939751
        ],
        [
          1733.1968419644058,
          544.9011998751068
        ],
        [
          356.7817476247833,
          544.9011998751068
        ]
      ],
      "group_id": 11,
      "description": "",
      "difficult": false,
      "shape_type": "rectangle",
      "flags": {},
      "attributes": {}
    },
    {
      "label": "cdark",
      "points": [
        [
          355.71791783754804,
          573.2918506623844
        ],
        [
          1732.1330121771707,
          573.2918506623844
        ],
        [
          1732.1330121771707,
          594.9899638699317
        ],
        [
          355.71791783754804,
          594.9899638699317
        ]
      ],
      "group_id": 12,
      "description": "",
      "difficult": false,
      "shape_type": "rectangle",
      "flags": {},
      "attributes": {}
    },
    {
      "label": "cdark",
      "points": [
        [
          350.8176100628933,
          621.4150943396227
        ],
        [
          1732.8930817610062,
          621.4150943396227
        ],
        [
          1732.8930817610062,
          644.0566037735849
        ],
        [
          350.8176100628933,
          644.0566037735849
        ]
      ],
      "group_id": 13,
      "description": "",
      "difficult": false,
      "shape_type": "rectangle",
      "flags": {},
      "attributes": {}
    },
    {
      "label": "cdark",
      "points": [
        [
          353.37526205450786,
          665.5296846424905
        ],
        [
          1729.7903563941302,
          665.5296846424905
        ],
        [
          1729.7903563941302,
          687.2277978500376
        ],
        [
          353.37526205450786,
          687.2277978500376
        ]
      ],
      "group_id": 14,
      "description": "",
      "difficult": false,
      "shape_type": "rectangle",
      "flags": {},
      "attributes": {}
    },
    {
      "label": "cdark",
      "points": [
        [
          357.1488469601676,
          707.0707881707476
        ],
        [
          1729.79035639413,
          707.0707881707476
        ],
        [
          1729.79035639413,
          729.3710691823895
        ],
        [
          357.1488469601676,
          729.3710691823895
        ]
      ],
      "group_id": 15,
      "description": "",
      "difficult": false,
      "shape_type": "rectangle",
      "flags": {},
      "attributes": {}
    },
    {
      "label": "cdark",
      "points": [
        [
          358.7631027253663,
          754.9431285962804
        ],
        [
          1735.178197064989,
          754.9431285962804
        ],
        [
          1735.178197064989,
          777.5846380302427
        ],
        [
          358.7631027253663,
          777.5846380302427
        ]
      ],
      "group_id": 16,
      "description": "",
      "difficult": false,
      "shape_type": "rectangle",
      "flags": {},
      "attributes": {}
    },
    {
      "label": "cdark",
      "points": [
        [
          359.491502743209,
          804.234800838575
        ],
        [
          1731.069182389937,
          804.234800838575
        ],
        [
          1731.069182389937,
          825.9329140461219
        ],
        [
          359.491502743209,
          825.9329140461219
        ]
      ],
      "group_id": 17,
      "description": "",
      "difficult": false,
      "shape_type": "rectangle",
      "flags": {},
      "attributes": {}
    },
    {
      "label": "cdark",
      "points": [
        [
          364.29724787010963,
          850.1257861635219
        ],
        [
          1736.457023060797,
          850.1257861635219
        ],
        [
          1736.457023060797,
          871.8238993710689
        ],
        [
          364.29724787010963,
          871.8238993710689
        ]
      ],
      "group_id": 18,
      "description": "",
      "difficult": false,
      "shape_type": "rectangle",
      "flags": {},
      "attributes": {}
    },
    {
      "label": "cdark",
      "points": [
        [
          359.09853249475947,
          893.7945492662475
        ],
        [
          1736.457023060797,
          893.7945492662475
        ],
        [
          1736.457023060797,
          915.2517953521569
        ],
        [
          359.09853249475947,
          915.2517953521569
        ]
      ],
      "group_id": 19,
      "description": "",
      "difficult": false,
      "shape_type": "rectangle",
      "flags": {},
      "attributes": {}
    },
    {
      "label": "cdark",
      "points": [
        [
          361.20032115616317,
          943.7428074401171
        ],
        [
          1744.3396226415102,
          943.7428074401171
        ],
        [
          1744.3396226415102,
          964.2767295597475
        ],
        [
          361.20032115616317,
          964.2767295597475
        ]
      ],
      "group_id": 20,
      "description": "",
      "difficult": false,
      "shape_type": "rectangle",
      "flags": {},
      "attributes": {}
    },
    {
      "label": "cdark",
      "points": [
        [
          363.54297693920313,
          995.1362683438158
        ],
        [
          1743.7316561844864,
          995.1362683438158
        ],
        [
          1743.7316561844864,
          1017.7777777777776
        ],
        [
          363.54297693920313,
          1017.7777777777776
        ]
      ],
      "group_id": 21,
      "description": "",
      "difficult": false,
      "shape_type": "rectangle",
      "flags": {},
      "attributes": {}
    },
    {
      "label": "cdark",
      "points": [
        [
          366.3731656184485,
          1036.1970649895197
        ],
        [
          1741.8448637316556,
          1036.1970649895197
        ],
        [
          1741.8448637316556,
          1057.8951781970666
        ],
        [
          366.3731656184485,
          1057.8951781970666
        ]
      ],
      "group_id": 22,
      "description": "",
      "difficult": false,
      "shape_type": "rectangle",
      "flags": {},
      "attributes": {}
    },
    {
      "label": "cdark",
      "points": [
        [
          363.20754716981037,
          11.979035639414505
        ],
        [
          1740.5660377358495,
          11.979035639414505
        ],
        [
          1740.5660377358495,
          35.56394129979138
        ],
        [
          363.20754716981037,
          35.56394129979138
        ]
      ],
      "group_id": 23,
      "description": "",
      "difficult": false,
      "shape_type": "rectangle",
      "flags": {},
      "attributes": {}
    },
    {
      "label": "cdark",
      "points": [
        [
          368.59538784067064,
          58.813417190774445
        ],
        [
          1741.236897274634,
          58.813417190774445
        ],
        [
          1741.236897274634,
          78.0020964360573
        ],
        [
          368.59538784067064,
          78.0020964360573
        ]
      ],
      "group_id": 1,
      "description": "",
      "difficult": false,
      "shape_type": "rectangle",
      "flags": {},
      "attributes": {}
    },
    {
      "label": "cdark",
      "points": [
        [
          356.6666666666669,
          108.99999999999996
        ],
        [
          1727.7777777777794,
          108.99999999999996
        ],
        [
          1727.7777777777794,
          126.77777777777811
        ],
        [
          356.6666666666669,
          126.77777777777811
        ]
      ],
      "group_id": 2,
      "description": "",
      "difficult": false,
      "shape_type": "rectangle",
      "flags": {},
      "attributes": {}
    },
    {
      "label": "cdark",
      "points": [
        [
          356.6666666666665,
          157.99999999999935
        ],
        [
          1736.6666666666674,
          157.99999999999935
        ],
        [
          1736.6666666666674,
          177.9999999999992
        ],
        [
          356.6666666666665,
          177.9999999999992
        ]
      ],
      "group_id": 3,
      "description": "",
      "difficult": false,
      "shape_type": "rectangle",
      "flags": {},
      "attributes": {}
    },
    {
      "label": "cdark",
      "points": [
        [
          361.1111111111112,
          200.3333333333336
        ],
        [
          1732.2222222222215,
          200.3333333333336
        ],
        [
          1732.2222222222215,
          218.1111111111113
        ],
        [
          361.1111111111112,
          218.1111111111113
        ]
      ],
      "group_id": 4,
      "description": "",
      "difficult": false,
      "shape_type": "rectangle",
      "flags": {},
      "attributes": {}
    }
  ],
  "imagePath": "frame_044970.jpg",
  "imageData": null,
  "imageHeight": 1080,
  "imageWidth": 2100
}