{
  "version": "2.3.6",
  "flags": {},
  "shapes": [
    {
      "label": "cdark",
      "points": [
        [
          363.3333333333333,
          74.44444444444433
        ],
        [
          1741.1111111111109,
          74.44444444444433
        ],
        [
          1741.1111111111109,
          94.44444444444434
        ],
        [
          363.3333333333333,
          94.44444444444434
        ]
      ],
      "group_id": 2,
      "description": "",
      "difficult": false,
      "shape_type": "rectangle",
      "flags": {},
      "attributes": {}
    },
    {
      "label": "cdark",
      "points": [
        [
          361.11111111111114,
          121.11111111111092
        ],
        [
          1725.5555555555557,
          121.11111111111092
        ],
        [
          1725.5555555555557,
          138.8888888888887
        ],
        [
          361.11111111111114,
          138.8888888888887
        ]
      ],
      "group_id": 3,
      "description": "",
      "difficult": false,
      "shape_type": "rectangle",
      "flags": {},
      "attributes": {}
    },
    {
      "label": "cdark",
      "points": [
        [
          358.8888888888892,
          167.7777777777775
        ],
        [
          1730.0000000000002,
          167.7777777777775
        ],
        [
          1730.0000000000002,
          187.7777777777775
        ],
        [
          358.8888888888892,
          187.7777777777775
        ]
      ],
      "group_id": 4,
      "description": "",
      "difficult": false,
      "shape_type": "rectangle",
      "flags": {},
      "attributes": {}
    },
    {
      "label": "cdark",
      "points": [
        [
          358.88888888888914,
          212.22222222222217
        ],
        [
          1732.2222222222222,
          212.22222222222217
        ],
        [
          1732.2222222222222,
          232.22222222222217
        ],
        [
          358.88888888888914,
          232.22222222222217
        ]
      ],
      "group_id": 5,
      "description": "",
      "difficult": false,
      "shape_type": "rectangle",
      "flags": {},
      "attributes": {}
    },
    {
      "label": "cdark",
      "points": [
        [
          363.3333333333335,
          256.6666666666667
        ],
        [
          1734.4444444444446,
          256.6666666666667
        ],
        [
          1734.4444444444446,
          276.6666666666667
        ],
        [
          363.3333333333335,
          276.6666666666667
        ]
      ],
      "group_id": 6,
      "description": "",
      "difficult": false,
      "shape_type": "rectangle",
      "flags": {},
      "attributes": {}
    },
    {
      "label": "cdark",
      "points": [
        [
          367.7777777777779,
          298.888888888889
        ],
        [
          1732.2222222222222,
          298.888888888889
        ],
        [
          1732.2222222222222,
          318.888888888889
        ],
        [
          367.7777777777779,
          318.888888888889
        ]
      ],
      "group_id": 7,
      "description": "",
      "difficult": false,
      "shape_type": "rectangle",
      "flags": {},
      "attributes": {}
    },
    {
      "label": "cdark",
      "points": [
        [
          361.1111111111112,
          347.7777777777777
        ],
        [
          1725.5555555555557,
          347.7777777777777
        ],
        [
          1725.5555555555557,
          369.99999999999994
        ],
        [
          361.1111111111112,
          369.99999999999994
        ]
      ],
      "group_id": 8,
      "description": "",
      "difficult": false,
      "shape_type": "rectangle",
      "flags": {},
      "attributes": {}
    },
    {
      "label": "cdark",
      "points": [
        [
          356.66666666666686,
          396.66666666666674
        ],
        [
          1727.7777777777778,
          396.66666666666674
        ],
        [
          1727.7777777777778,
          416.66666666666674
        ],
        [
          356.66666666666686,
          416.66666666666674
        ]
      ],
      "group_id": 9,
      "description": "",
      "difficult": false,
      "shape_type": "rectangle",
      "flags": {},
      "attributes": {}
    },
    {
      "label": "cdark",
      "points": [
        [
          365.5555555555553,
          445.5555555555553
        ],
        [
          1734.4444444444443,
          445.5555555555553
        ],
        [
          1734.4444444444443,
          465.5555555555553
        ],
        [
          365.5555555555553,
          465.5555555555553
        ]
      ],
      "group_id": 10,
      "description": "",
      "difficult": false,
      "shape_type": "rectangle",
      "flags": {},
      "attributes": {}
    },
    {
      "label": "cdark",
      "points": [
        [
          361.1111111111109,
          489.9999999999998
        ],
        [
          1727.7777777777783,
          489.9999999999998
        ],
        [
          1727.7777777777783,
          509.9999999999998
        ],
        [
          361.1111111111109,
          509.9999999999998
        ]
      ],
      "group_id": 11,
      "description": "",
      "difficult": false,
      "shape_type": "rectangle",
      "flags": {},
      "attributes": {}
    },
    {
      "label": "cdark",
      "points": [
        [
          363.3333333333335,
          536.6666666666664
        ],
        [
          1734.4444444444443,
          536.6666666666664
        ],
        [
          1734.4444444444443,
          556.6666666666664
        ],
        [
          363.3333333333335,
          556.6666666666664
        ]
      ],
      "group_id": 12,
      "description": "",
      "difficult": false,
      "shape_type": "rectangle",
      "flags": {},
      "attributes": {}
    },
    {
      "label": "cdark",
      "points": [
        [
          365.5555555555555,
          581.1111111111112
        ],
        [
          1729.9999999999995,
          581.1111111111112
        ],
        [
          1729.9999999999995,
          607.7777777777779
        ],
        [
          365.5555555555555,
          607.7777777777779
        ]
      ],
      "group_id": 13,
      "description": "",
      "difficult": false,
      "shape_type": "rectangle",
      "flags": {},
      "attributes": {}
    },
    {
      "label": "cdark",
      "points": [
        [
          365.5555555555552,
          627.7777777777779
        ],
        [
          1734.4444444444443,
          627.7777777777779
        ],
        [
          1734.4444444444443,
          654.4444444444447
        ],
        [
          365.5555555555552,
          654.4444444444447
        ]
      ],
      "group_id": 14,
      "description": "",
      "difficult": false,
      "shape_type": "rectangle",
      "flags": {},
      "attributes": {}
    },
    {
      "label": "cdark",
      "points": [
        [
          367.7777777777781,
          672.2222222222225
        ],
        [
          1736.6666666666665,
          672.2222222222225
        ],
        [
          1736.6666666666665,
          694.4444444444448
        ],
        [
          367.7777777777781,
          694.4444444444448
        ]
      ],
      "group_id": 15,
      "description": "",
      "difficult": false,
      "shape_type": "rectangle",
      "flags": {},
      "attributes": {}
    },
    {
      "label": "cdark",
      "points": [
        [
          369.99999999999994,
          723.3333333333333
        ],
        [
          1727.777777777778,
          723.3333333333333
        ],
        [
          1727.777777777778,
          743.3333333333333
        ],
        [
          369.99999999999994,
          743.3333333333333
        ]
      ],
      "group_id": 16,
      "description": "",
      "difficult": false,
      "shape_type": "rectangle",
      "flags": {},
      "attributes": {}
    },
    {
      "label": "cdark",
      "points": [
        [
          365.55555555555566,
          767.7777777777777
        ],
        [
          1743.3333333333335,
          767.7777777777777
        ],
        [
          1743.3333333333335,
          783.3333333333333
        ],
        [
          365.55555555555566,
          783.3333333333333
        ]
      ],
      "group_id": 17,
      "description": "",
      "difficult": false,
      "shape_type": "rectangle",
      "flags": {},
      "attributes": {}
    },
    {
      "label": "cdark",
      "points": [
        [
          361.11111111111126,
          814.4444444444446
        ],
        [
          1732.2222222222222,
          814.4444444444446
        ],
        [
          1732.2222222222222,
          836.6666666666667
        ],
        [
          361.11111111111126,
          836.6666666666667
        ]
      ],
      "group_id": 18,
      "description": "",
      "difficult": false,
      "shape_type": "rectangle",
      "flags": {},
      "attributes": {}
    },
    {
      "label": "cdark",
      "points": [
        [
          369.99999999999983,
          856.6666666666664
        ],
        [
          1741.1111111111109,
          856.6666666666664
        ],
        [
          1741.1111111111109,
          876.6666666666664
        ],
        [
          369.99999999999983,
          876.6666666666664
        ]
      ],
      "group_id": 19,
      "description": "",
      "difficult": false,
      "shape_type": "rectangle",
      "flags": {},
      "attributes": {}
    },
    {
      "label": "cdark",
      "points": [
        [
          369.9999999999999,
          907.7777777777784
        ],
        [
          1743.333333333333,
          907.7777777777784
        ],
        [
          1743.333333333333,
          927.7777777777784
        ],
        [
          369.9999999999999,
          927.7777777777784
        ]
      ],
      "group_id": 20,
      "description": "",
      "difficult": false,
      "shape_type": "rectangle",
      "flags": {},
      "attributes": {}
    },
    {
      "label": "cdark",
      "points": [
        [
          367.77777777777794,
          950.0000000000001
        ],
        [
          1743.3333333333333,
          950.0000000000001
        ],
        [
          1743.3333333333333,
          967.7777777777779
        ],
        [
          367.77777777777794,
          967.7777777777779
        ]
      ],
      "group_id": 21,
      "description": "",
      "difficult": false,
      "shape_type": "rectangle",
      "flags": {},
      "attributes": {}
    },
    {
      "label": "cdark",
      "points": [
        [
          365.5555555555555,
          1001.1111111111115
        ],
        [
          1741.1111111111109,
          1001.1111111111115
        ],
        [
          1741.1111111111109,
          1025.5555555555557
        ],
        [
          365.5555555555555,
          1025.5555555555557
        ]
      ],
      "group_id": 22,
      "description": "",
      "difficult": false,
      "shape_type": "rectangle",
      "flags": {},
      "attributes": {}
    },
    {
      "label": "cdark",
      "points": [
        [
          358.88888888888886,
          30.000000000000014
        ],
        [
          1738.8888888888887,
          30.000000000000014
        ],
        [
          1738.8888888888887,
          47.7777777777779
        ],
        [
          358.88888888888886,
          47.7777777777779
        ]
      ],
      "group_id": 1,
      "description": "",
      "difficult": false,
      "shape_type": "rectangle",
      "flags": {},
      "attributes": {}
    },
    {
      "label": "cdark",
      "points": [
        [
          365.55555555555554,
          1061.111111111111
        ],
        [
          1745.5555555555554,
          1061.111111111111
        ],
        [
          1745.5555555555554,
          1080.3333333333333
        ],
        [
          365.55555555555554,
          1080.3333333333333
        ]
      ],
      "group_id": 1,
      "description": "",
      "difficult": false,
      "shape_type": "rectangle",
      "flags": {},
      "attributes": {}
    }
  ],
  "imagePath": "frame_034530.jpg",
  "imageData": null,
  "imageHeight": 1080,
  "imageWidth": 2100
}